bootstrapped/__init__.py
bootstrapped/bootstrap.py
bootstrapped/compare_functions.py
bootstrapped/permutation.py
bootstrapped/power.py
bootstrapped/stats_functions.py
bootstrapped_ng-0.1.3.dist-info/LICENSE
bootstrapped_ng-0.1.3.dist-info/LICENSE-examples
bootstrapped_ng-0.1.3.dist-info/METADATA
bootstrapped_ng-0.1.3.dist-info/WHEEL
bootstrapped_ng-0.1.3.dist-info/top_level.txt
bootstrapped_ng-0.1.3.dist-info/RECORD
