Metadata-Version: 2.1
Name: bootstrapped-ng
Version: 0.1.3
Summary: Implementations of the percentile based bootstrap - forked
Home-page: https://github.com/athenianco/bootstrapped
Author: Spencer Beecher
Author-email: spencebeecher@gmail.com
Maintainer: Vadim Markovtsev
Maintainer-email: vadim@athenian.co
Classifier: Development Status :: 5 - Production/Stable
Classifier: License :: OSI Approved :: BSD License
Requires-Python: >=3.10.0
License-File: LICENSE
License-File: LICENSE-examples
Requires-Dist: numpy (>=1.11.1)
Requires-Dist: scipy (>=0.19.1)
Provides-Extra: power
Requires-Dist: matplotlib (>=1.5.3) ; extra == 'power'
Requires-Dist: pandas (>=0.18.1) ; extra == 'power'
